.gitignore
CHANGELOG
LICENSE
Makefile
Makefile.fk
README.md
VERSION
project.qbs
setup.cfg
setup.py
./LICENSE
.gitlab/ci.yaml
code_quality/.flake8
code_quality/Makefile
code_quality/mypy.ini
code_quality/pylintrc
design/logo-1024.png
design/logo-1024.svg
quarantine/db/Connection.py
quarantine/db/DatabaseConnection.py
quarantine/db/DatabaseConnectionAsync.py
quarantine/db/Influx.py
quarantine/db/utils.py
requirements/requirements.in
requirements/requirements.txt
requirements/test_requirements.in
requirements/test_requirements.txt
resources/images/profile.svg
resources/images/logos/1024px.png
resources/images/logos/1024px.svg
resources/images/logos/16px.png
resources/images/logos/16px.svg
resources/templates/README.md
src/octomy/access/__init__.py
src/octomy/access/grants/__init__.py
src/octomy/access/groups/__init__.py
src/octomy/access/password_resets/__init__.py
src/octomy/access/user_group_relations/__init__.py
src/octomy/access/users/__init__.py
src/octomy/config/__init__.py
src/octomy/db/__init__.py
src/octomy/db/check.py
src/octomy/log/__init__.py
src/octomy/storage/__init__.py
src/octomy/storage/google_drive.py
src/octomy/utils/Profiler.py
src/octomy/utils/Svg.py
src/octomy/utils/Watchdog.py
src/octomy/utils/WorkerPool.py
src/octomy/utils/__init__.py
src/octomy/utils/click.py
src/octomy/utils/credentials.py
src/octomy/utils/csv_to_db.py
src/octomy/utils/debug_view.py
src/octomy/utils/excavator.py
src/octomy/utils/expiry_cache.py
src/octomy/version/__init__.py
src/octomy/web/__init__.py
src/octomy/web/autoroute.py
src/octomy/web/context/__init__.py
src/octomy/web/search/__init__.py
src/octomy_common.egg-info/PKG-INFO
src/octomy_common.egg-info/SOURCES.txt
src/octomy_common.egg-info/dependency_links.txt
src/octomy_common.egg-info/namespace_packages.txt
src/octomy_common.egg-info/requires.txt
src/octomy_common.egg-info/top_level.txt
src/octomy_common.egg-info/zip-safe
tests/Makefile
tests/__init__.py
tests/pytest.ini
tests/integration/__init__.py
tests/integration/test_true.py
tests/load/__init__.py
tests/load/test_true.py
tests/unit/__init__.py
tests/unit/test_context.py
tests/unit/test_db.py
tests/unit/test_generator_openscad.py
tests/unit/test_openscad.py
tests/unit/test_parts.py
tests/unit/test_termcols.py
tests/unit/test_util.py
