Metadata-Version: 2.1
Name: octomy-common
Version: 2.0.56
Summary: octomy/common
Home-page: https://gitlab.com/octomy/common
Author: OctoMY
Author-email: pypi@octomy.org
Maintainer: OctoMY
Maintainer-email: pypi@octomy.org
License: Proprietary Software License
Project-URL: Docs, https://gitlab.com/octomy/common//-/blob/production/README.md
Project-URL: Bugs, https://gitlab.com/octomy/common/issues
Project-URL: C.I., https://gitlab.com/octomy/common/pipelines
Keywords: software
Platform: Linux
Classifier: Development Status :: 1 - Planning
Classifier: Intended Audience :: Developers
Classifier: Intended Audience :: Information Technology
Classifier: Intended Audience :: Science/Research
Classifier: Intended Audience :: Other Audience
Classifier: Topic :: Utilities
Classifier: Natural Language :: English
Classifier: Operating System :: POSIX :: Linux
Classifier: Programming Language :: Python :: 3.10
Classifier: Topic :: Other/Nonlisted Topic
Requires-Python: >=3.10
License-File: ./LICENSE
